MANIFEST.in
README
requirements.txt
setup.py
ajenti.plugin.check_certificates.egg-info/PKG-INFO
ajenti.plugin.check_certificates.egg-info/SOURCES.txt
ajenti.plugin.check_certificates.egg-info/dependency_links.txt
ajenti.plugin.check_certificates.egg-info/requires.txt
ajenti.plugin.check_certificates.egg-info/top_level.txt
ajenti_plugin_check_certificates/README.md
ajenti_plugin_check_certificates/__init__.py
ajenti_plugin_check_certificates/api.py
ajenti_plugin_check_certificates/main.py
ajenti_plugin_check_certificates/plugin.yml
ajenti_plugin_check_certificates/requirements.txt
ajenti_plugin_check_certificates/views.py
ajenti_plugin_check_certificates/widget.py
ajenti_plugin_check_certificates/locale/app.pot
ajenti_plugin_check_certificates/locale/af/LC_MESSAGES/app.js
ajenti_plugin_check_certificates/locale/af/LC_MESSAGES/app.po
ajenti_plugin_check_certificates/locale/ar/LC_MESSAGES/app.js
ajenti_plugin_check_certificates/locale/ar/LC_MESSAGES/app.po
ajenti_plugin_check_certificates/locale/be/LC_MESSAGES/app.js
ajenti_plugin_check_certificates/locale/be/LC_MESSAGES/app.po
ajenti_plugin_check_certificates/locale/bg/LC_MESSAGES/app.js
ajenti_plugin_check_certificates/locale/bg/LC_MESSAGES/app.po
ajenti_plugin_check_certificates/locale/bn/LC_MESSAGES/app.js
ajenti_plugin_check_certificates/locale/bn/LC_MESSAGES/app.po
ajenti_plugin_check_certificates/locale/bs/LC_MESSAGES/app.js
ajenti_plugin_check_certificates/locale/bs/LC_MESSAGES/app.po
ajenti_plugin_check_certificates/locale/ca/LC_MESSAGES/app.js
ajenti_plugin_check_certificates/locale/ca/LC_MESSAGES/app.po
ajenti_plugin_check_certificates/locale/cs/LC_MESSAGES/app.js
ajenti_plugin_check_certificates/locale/cs/LC_MESSAGES/app.po
ajenti_plugin_check_certificates/locale/da/LC_MESSAGES/app.js
ajenti_plugin_check_certificates/locale/da/LC_MESSAGES/app.po
ajenti_plugin_check_certificates/locale/de/LC_MESSAGES/app.js
ajenti_plugin_check_certificates/locale/de/LC_MESSAGES/app.po
ajenti_plugin_check_certificates/locale/el/LC_MESSAGES/app.js
ajenti_plugin_check_certificates/locale/el/LC_MESSAGES/app.po
ajenti_plugin_check_certificates/locale/en/LC_MESSAGES/app.po
ajenti_plugin_check_certificates/locale/eo/LC_MESSAGES/app.js
ajenti_plugin_check_certificates/locale/eo/LC_MESSAGES/app.po
