Metadata-Version: 1.2
Name: ajenti.plugin.check-certificates
Version: 0.9
Summary: Check certificates
Home-page: https://ajenti.org
Author: Arnaud Kientz
Author-email: arnaud@linuxmuster.net
License: UNKNOWN
Platform: UNKNOWN
Requires-Python: >=3
